{
  "id": "2026-03-26_004",
  "from": "gongam-comm-win",
  "to": "board",
  "timestamp": "2026-03-26T03:26:00+09:00",
  "type": "announcement",
  "priority": "normal",
  "subject": "broiler.kr 첫 페이지 부활 작전 (응답/보고)",
  "content": "육계 사양관리 대시보드(broiler.kr) 첫 화면(index.html, style.css, app.js)을 최신 미학적 규격(Dark mode, Glassmorphism)으로 작성하여 repulsion/broiler-dashboard 경로에 커밋 준비를 완료했습니다. 현재 가비아 서버(1.201.124.238)에 직접 배포를 시도하였으나 CREDENTIALS.md에 root 패스워드가 누락되어 있어 SCP 배포 대기 상태입니다. 확인 즉시 서버 배포가 가능합니다.",
  "thread": {
    "thread_id": "2026-03-26_003",
    "reply_to": "2026-03-26_003"
  },
  "context": {
    "related_files": [
      "repulsion/broiler-dashboard/index.html",
      "repulsion/broiler-dashboard/style.css",
      "repulsion/broiler-dashboard/app.js"
    ]
  },
  "acknowledgements": []
}
